{"frames":{"mediumBugDeath0.png":{"frame":{"x":0,"y":0,"w":28,"h":38},"rotated":false,"trimmed":false,"spriteSourceSize":{"x":0,"y":0,"w":28,"h":38},"sourceSize":{"w":28,"h":38}},"mediumBugDeath1.png":{"frame":{"x":0,"y":38,"w":28,"h":38},"rotated":false,"trimmed":false,"spriteSourceSize":{"x":0,"y":0,"w":28,"h":38},"sourceSize":{"w":28,"h":38}},"mediumBugDeath2.png":{"frame":{"x":0,"y":76,"w":28,"h":38},"rotated":false,"trimmed":false,"spriteSourceSize":{"x":0,"y":0,"w":28,"h":38},"sourceSize":{"w":28,"h":38}},"mediumBugDeath3.png":{"frame":{"x":0,"y":114,"w":28,"h":38},"rotated":false,"trimmed":false,"spriteSourceSize":{"x":0,"y":0,"w":28,"h":38},"sourceSize":{"w":28,"h":38}},"mediumBugDeath4.png":{"frame":{"x":0,"y":152,"w":28,"h":38},"rotated":false,"trimmed":false,"spriteSourceSize":{"x":0,"y":0,"w":28,"h":38},"sourceSize":{"w":28,"h":38}},"mediumBugDeath5.png":{"frame":{"x":0,"y":190,"w":28,"h":38},"rotated":false,"trimmed":false,"spriteSourceSize":{"x":0,"y":0,"w":28,"h":38},"sourceSize":{"w":28,"h":38}},"mediumBugDeath6.png":{"frame":{"x":0,"y":228,"w":28,"h":38},"rotated":false,"trimmed":false,"spriteSourceSize":{"x":0,"y":0,"w":28,"h":38},"sourceSize":{"w":28,"h":38}}},"meta":{"app":"https://github.com/juliandescottes/piskel/","version":"1.0","image":"mediumBugDeath.png","format":"RGBA8888","size":{"w":28,"h":266}}}